brrr/__init__.py
brrr/audio.py
brrr/skrrrahh.py
brrr/adlibs/bigboi.wav
brrr/adlibs/biggie.wav
brrr/adlibs/bigsean.wav
brrr/adlibs/bigsean1.wav
brrr/adlibs/bigsean2.wav
brrr/adlibs/bigsean3.wav
brrr/adlibs/bigsean4.wav
brrr/adlibs/bigsean5.wav
brrr/adlibs/bigshaq.wav
brrr/adlibs/birdman.wav
brrr/adlibs/birdman1.wav
brrr/adlibs/birdman2.wav
brrr/adlibs/busta.wav
brrr/adlibs/chance.wav
brrr/adlibs/desiigner.wav
brrr/adlibs/diddy.wav
brrr/adlibs/drake.wav
brrr/adlibs/drake1.wav
brrr/adlibs/drummaboy.wav
brrr/adlibs/fetty.wav
brrr/adlibs/flava.wav
brrr/adlibs/future.wav
brrr/adlibs/gucci.wav
brrr/adlibs/gucci1.wav
brrr/adlibs/gucci2.wav
brrr/adlibs/jayz.wav
brrr/adlibs/jayz1.wav.wav
brrr/adlibs/kendrick.wav
brrr/adlibs/khaled.wav
brrr/adlibs/khaled1.wav
brrr/adlibs/khaled2.wav
brrr/adlibs/khaled3.wav
brrr/adlibs/liljon.wav
brrr/adlibs/liljon1.wav
brrr/adlibs/nicki.wav
brrr/adlibs/pitbull.wav
brrr/adlibs/ross.wav
brrr/adlibs/ross1.wav
brrr/adlibs/schoolboy.wav
brrr/adlibs/snoop.wav
brrr/adlibs/soulja.wav
brrr/adlibs/takeoff.wav
brrr/adlibs/tpain.wav
brrr/adlibs/traviscott.wav
brrr/adlibs/treysongz.wav
brrr/adlibs/trick.wav
brrr/adlibs/twochainz.wav
brrr/adlibs/twochainz1.wav
brrr/adlibs/waka.wav
brrr/adlibs/weezy.wav
brrr/adlibs/yg.wav
brrr-0.12.dist-info/DESCRIPTION.rst
brrr-0.12.dist-info/METADATA
brrr-0.12.dist-info/RECORD
brrr-0.12.dist-info/WHEEL
brrr-0.12.dist-info/metadata.json
brrr-0.12.dist-info/top_level.txt
