Metadata-Version: 2.0
Name: brrr
Version: 0.12
Summary: Let Gucci Mane tell you when your script is done.
Home-page: https://github.com/dominikstrb/brrr
Author: Dominik Straub
Author-email: dstraub93@gmail.com
License: UNKNOWN
Download-URL: https://github.com/dominikstrb/brrr/archive/master.zip
Keywords: gucci,skrrrahh,brrr
Platform: UNKNOWN
Requires-Python: >=3
